codefast/__init__.py
codefast/argparser.py
codefast/concurrency.py
codefast/logger.py
codefast/simple_parser.py
codefast/utils.py
cfwp-0.0.1.dist-info/LICENSE
cfwp-0.0.1.dist-info/METADATA
cfwp-0.0.1.dist-info/WHEEL
cfwp-0.0.1.dist-info/top_level.txt
cfwp-0.0.1.dist-info/RECORD
